LICENSE
MANIFEST.in
README.rst
atomiclong.py
setup.py
test_atomiclong.py
__pycache__/_cffi__x50e71d72xf96f5519.c
atomiclong.egg-info/PKG-INFO
atomiclong.egg-info/SOURCES.txt
atomiclong.egg-info/dependency_links.txt
atomiclong.egg-info/not-zip-safe
atomiclong.egg-info/requires.txt
atomiclong.egg-info/top_level.txt