Metadata-Version: 1.0
Name: atomiclong
Version: 0.1.1
Summary: An AtomicLong type using CFFI.
Home-page: https://github.com/dreid/atomiclong
Author: David Reid
Author-email: dreid@dreid.org
License: MIT
Platform: UNKNOWN
